<annotation>
	<folder></folder>
	<filename>CarLongPlateGen2869_jpg.rf.f0fae32142507333cb84108f438460ca.jpg</filename>
	<path>CarLongPlateGen2869_jpg.rf.f0fae32142507333cb84108f438460ca.jpg</path>
	<source>
		<database>roboflow.com</database>
	</source>
	<size>
		<width>472</width>
		<height>303</height>
		<depth>3</depth>
	</size>
	<segmented>0</segmented>
	<object>
		<name>License_Plate</name>
		<pose>Unspecified</pose>
		<truncated>0</truncated>
		<difficult>0</difficult>
		<occluded>0</occluded>
		<bndbox>
			<xmin>96</xmin>
			<xmax>211</xmax>
			<ymin>208</ymin>
			<ymax>240</ymax>
		</bndbox>
	</object>
	<metadata>
	</metadata>
</annotation>
