<annotation>
	<folder></folder>
	<filename>CarLongPlateGen3327_jpg.rf.b080ffeaa6a7395d9f9537bf9e6ce7ee.jpg</filename>
	<path>CarLongPlateGen3327_jpg.rf.b080ffeaa6a7395d9f9537bf9e6ce7ee.jpg</path>
	<source>
		<database>roboflow.com</database>
	</source>
	<size>
		<width>472</width>
		<height>303</height>
		<depth>3</depth>
	</size>
	<segmented>0</segmented>
	<object>
		<name>License_Plate</name>
		<pose>Unspecified</pose>
		<truncated>0</truncated>
		<difficult>0</difficult>
		<occluded>0</occluded>
		<bndbox>
			<xmin>208</xmin>
			<xmax>308</xmax>
			<ymin>79</ymin>
			<ymax>115</ymax>
		</bndbox>
	</object>
	<metadata>
	</metadata>
</annotation>
